wagtail_html_editor/__init__.py
wagtail_html_editor/apps.py
wagtail_html_editor/blocks.py
wagtail_html_editor/settings.py
wagtail_html_editor/telepath.py
wagtail_html_editor/wagtail_hooks.py
wagtail_html_editor/widgets.py
wagtail_html_editor/static/wagtail_html_editor/css/.gitkeep
wagtail_html_editor/static/wagtail_html_editor/css/wagtail-html-editor.css
wagtail_html_editor/static/wagtail_html_editor/js/wagtail-html-editor.iife.js
wagtail_html_editor/static/wagtail_html_editor/js/wagtail-html-editor.iife.js.map
wagtail_html_editor/static/wagtail_html_editor/js/wagtail-html-editor.js
wagtail_html_editor/static/wagtail_html_editor/js/wagtail-html-editor.js.map
wagtail_html_editor/templates/wagtail_html_editor/.gitkeep
wagtail_html_editor/templates/wagtail_html_editor/widgets/enhanced_html.html
wagtail_html_editor-1.0.0.dist-info/METADATA
wagtail_html_editor-1.0.0.dist-info/WHEEL
wagtail_html_editor-1.0.0.dist-info/licenses/LICENSE
wagtail_html_editor-1.0.0.dist-info/RECORD
