Metadata-Version: 2.4
Name: wagtail-html-editor
Version: 1.0.0
Summary: Enhanced HTML editor block for Wagtail CMS with CodeMirror 6, syntax highlighting, Emmet support, and fullscreen mode
Project-URL: Homepage, https://github.com/kkm-horikawa/wagtail-html-editor
Project-URL: Documentation, https://github.com/kkm-horikawa/wagtail-html-editor#readme
Project-URL: Repository, https://github.com/kkm-horikawa/wagtail-html-editor.git
Project-URL: Issues, https://github.com/kkm-horikawa/wagtail-html-editor/issues
Project-URL: Changelog, https://github.com/kkm-horikawa/wagtail-html-editor/releases
Author: kkm-horikawa
License: BSD-3-Clause
License-File: LICENSE
Keywords: cms,codemirror,django,editor,emmet,html,wagtail
Classifier: Development Status :: 3 - Alpha
Classifier: Environment :: Web Environment
Classifier: Framework :: Django
Classifier: Framework :: Django :: 4.2
Classifier: Framework :: Django :: 5.1
Classifier: Framework :: Django :: 5.2
Classifier: Framework :: Wagtail
Classifier: Framework :: Wagtail :: 6
Classifier: Framework :: Wagtail :: 7
Classifier: Intended Audience :: Developers
Classifier: License :: OSI Approved :: BSD License
Classifier: Operating System :: OS Independent
Classifier: Programming Language :: Python :: 3
Classifier: Programming Language :: Python :: 3.10
Classifier: Programming Language :: Python :: 3.11
Classifier: Programming Language :: Python :: 3.12
Classifier: Programming Language :: Python :: 3.13
Classifier: Programming Language :: Python :: 3.14
Classifier: Topic :: Internet :: WWW/HTTP :: Dynamic Content
Requires-Python: >=3.10
Requires-Dist: django>=4.2
Requires-Dist: wagtail>=6.0
Provides-Extra: dev
Requires-Dist: django-stubs>=5.1; extra == 'dev'
Requires-Dist: mypy>=1.13; extra == 'dev'
Requires-Dist: pre-commit>=4.0; extra == 'dev'
Requires-Dist: pytest-cov>=4.1; extra == 'dev'
Requires-Dist: pytest-django>=4.8; extra == 'dev'
Requires-Dist: pytest>=8.0; extra == 'dev'
Requires-Dist: ruff>=0.8; extra == 'dev'
Requires-Dist: tox-uv>=1.0; extra == 'dev'
Requires-Dist: tox>=4.0; extra == 'dev'
